{
  "keyboard_name": "SparAkashaAnanta",
  "layouts": {
    "LAYOUT": {
      "layout": [
        {
          "x": 1.49,
          "y": -1.83,
          "r": 15,
          "rx": 1.49,
          "ry": -1.83,
          "matrix": [
            1,
            0
          ]
        },
        {
          "x": 2.52,
          "y": -2,
          "r": 15,
          "rx": 1.52,
          "ry": -2,
          "matrix": [
            2,
            0
          ]
        },
        {
          "x": 4.54,
          "y": -2.09,
          "r": 15,
          "rx": 2.54,
          "ry": -2.09,
          "matrix": [
            3,
            0
          ]
        },
        {
          "x": 3.58,
          "y": -2.43,
          "r": 15,
          "rx": 0.58,
          "ry": -2.43,
          "matrix": [
            4,
            0
          ]
        },
        {
          "x": 5.66,
          "y": -2.35,
          "r": 15,
          "rx": 1.66,
          "ry": -2.35,
          "matrix": [
            5,
            0
          ]
        },
        {
          "x": 6.71,
          "y": -2.35,
          "r": 15,
          "rx": 1.71,
          "ry": -2.35,
          "matrix": [
            2,
            1
          ]
        },
        {
          "x": 9.87,
          "y": 2.05,
          "r": -15,
          "rx": -1.13,
          "ry": 2.05,
          "matrix": [
            2,
            7
          ]
        },
        {
          "x": 10.9,
          "y": 2.05,
          "r": -15,
          "rx": -1.1,
          "ry": 2.05,
          "matrix": [
            5,
            6
          ]
        },
        {
          "x": 11.9,
          "y": 2.05,
          "r": -15,
          "rx": -1.1,
          "ry": 2.05,
          "matrix": [
            4,
            6
          ]
        },
        {
          "x": 12.93,
          "y": 2.22,
          "r": -15,
          "rx": -1.07,
          "ry": 2.22,
          "matrix": [
            3,
            6
          ]
        },
        {
          "x": 13.96,
          "y": 2.39,
          "r": -15,
          "rx": -1.04,
          "ry": 2.39,
          "matrix": [
            2,
            6
          ]
        },
        {
          "x": 14.99,
          "y": 2.56,
          "r": -15,
          "rx": -1.01,
          "ry": 2.56,
          "matrix": [
            1,
            6
          ]
        },
        {
          "x": 1.29,
          "y": -0.69,
          "r": 5,
          "rx": 1.29,
          "ry": -1.69,
          "matrix": [
            0,
            2
          ]
        },
        {
          "x": 2.29,
          "y": -0.69,
          "r": 5,
          "rx": 1.29,
          "ry": -1.69,
          "matrix": [
            1,
            2
          ]
        },
        {
          "x": 4.28,
          "y": -0.6,
          "r": 5,
          "rx": 2.28,
          "ry": -1.6,
          "matrix": [
            3,
            2
          ]
        },
        {
          "x": 3.29,
          "y": -0.78,
          "r": 5,
          "rx": 0.29,
          "ry": -1.78,
          "matrix": [
            4,
            2
          ]
        },
        {
          "x": 5.33,
          "y": -0.52,
          "r": 5,
          "rx": 1.33,
          "ry": -1.52,
          "matrix": [
            5,
            2
          ]
        },
        {
          "x": 6.36,
          "y": -0.35,
          "r": 5,
          "rx": 1.36,
          "ry": -1.35,
          "matrix": [
            3,
            1
          ]
        },
        {
          "x": 9.71,
          "y": 1.13,
          "r": -5,
          "rx": -1.29,
          "ry": 0.13,
          "matrix": [
            3,
            7
          ]
        },
        {
          "x": 10.71,
          "y": 0.96,
          "r": -5,
          "rx": -1.29,
          "ry": -0.04,
          "matrix": [
            5,
            8
          ]
        },
        {
          "x": 11.68,
          "y": 0.79,
          "r": -5,
          "rx": -1.32,
          "ry": -0.21,
          "matrix": [
            4,
            8
          ]
        },
        {
          "x": 12.68,
          "y": 0.79,
          "r": -5,
          "rx": -1.32,
          "ry": -0.21,
          "matrix": [
            3,
            8
          ]
        },
        {
          "x": 13.68,
          "y": 0.79,
          "r": -5,
          "rx": -1.32,
          "ry": -0.21,
          "matrix": [
            1,
            8
          ]
        },
        {
          "x": 14.68,
          "y": 0.79,
          "r": -5,
          "rx": -1.32,
          "ry": -0.21,
          "matrix": [
            0,
            8
          ]
        },
        {
          "x": 0.94,
          "y": 0.48,
          "r": -5,
          "rx": 0.94,
          "ry": -1.52,
          "matrix": [
            0,
            3
          ]
        },
        {
          "x": 1.94,
          "y": 0.66,
          "r": -5,
          "rx": 0.94,
          "ry": -1.34,
          "matrix": [
            1,
            3
          ]
        },
        {
          "x": 2.94,
          "y": 0.83,
          "r": -5,
          "rx": 0.94,
          "ry": -1.17,
          "matrix": [
            2,
            3
          ]
        },
        {
          "x": 3.94,
          "y": 1.01,
          "r": -5,
          "rx": 0.94,
          "ry": -0.99,
          "matrix": [
            4,
            3
          ]
        },
        {
          "x": 4.99,
          "y": 1.35,
          "r": -5,
          "rx": 0.99,
          "ry": -0.65,
          "matrix": [
            5,
            3
          ]
        },
        {
          "x": 6.01,
          "y": 1.7,
          "r": -5,
          "rx": 1.01,
          "ry": -0.3,
          "matrix": [
            4,
            1
          ]
        },
        {
          "x": 10.06,
          "y": 0.22,
          "r": 5,
          "rx": -0.94,
          "ry": -1.78,
          "matrix": [
            4,
            7
          ]
        },
        {
          "x": 11.06,
          "y": -0.13,
          "r": 5,
          "rx": -0.94,
          "ry": -2.13,
          "matrix": [
            5,
            9
          ]
        },
        {
          "x": 12.03,
          "y": -0.48,
          "r": 5,
          "rx": -0.97,
          "ry": -2.48,
          "matrix": [
            4,
            9
          ]
        },
        {
          "x": 13.03,
          "y": -0.65,
          "r": 5,
          "rx": -0.97,
          "ry": -2.65,
          "matrix": [
            2,
            9
          ]
        },
        {
          "x": 14.03,
          "y": -0.83,
          "r": 5,
          "rx": -0.97,
          "ry": -2.83,
          "matrix": [
            1,
            9
          ]
        },
        {
          "x": 15.03,
          "y": -1,
          "r": 5,
          "rx": -0.97,
          "ry": -3,
          "matrix": [
            0,
            9
          ]
        },
        {
          "x": 0.45,
          "y": 1.92,
          "r": -15,
          "rx": 0.45,
          "ry": -1.08,
          "matrix": [
            0,
            4
          ]
        },
        {
          "x": 1.42,
          "y": 2.27,
          "r": -15,
          "rx": 0.42,
          "ry": -0.73,
          "matrix": [
            1,
            4
          ]
        },
        {
          "x": 2.51,
          "y": 2.61,
          "r": -15,
          "rx": 0.51,
          "ry": -0.39,
          "matrix": [
            2,
            4
          ]
        },
        {
          "x": 5.25,
          "y": 2.25,
          "matrix": [
            3,
            4
          ]
        },
        {
          "x": 6.25,
          "y": 2.25,
          "matrix": [
            1,
            10
          ]
        },
        {
          "x": 9.75,
          "y": 2.25,
          "matrix": [
            2,
            5
          ]
        },
        {
          "x": 10.75,
          "y": 2.25,
          "matrix": [
            5,
            4
          ]
        },
        {
          "x": 13.97,
          "y": -1.79,
          "r": 15,
          "rx": -0.03,
          "ry": -4.79,
          "matrix": [
            5,
            10
          ]
        },
        {
          "x": 15,
          "y": -2.14,
          "r": 15,
          "rx": 0,
          "ry": -5.14,
          "matrix": [
            3,
            10
          ]
        },
        {
          "x": 16.03,
          "y": -2.48,
          "r": 15,
          "rx": 0.03,
          "ry": -5.48,
          "matrix": [
            2,
            10
          ]
        },
        {
          "x": 6.75,
          "y": 3.75,
          "w": 0.5,
          "h": 0.5,
          "matrix": [
            4,
            5
          ]
        },
        {
          "x": 7.25,
          "y": 3.25,
          "w": 0.5,
          "h": 0.5,
          "matrix": [
            0,
            10
          ]
        },
        {
          "x": 7.25,
          "y": 3.75,
          "w": 0.5,
          "h": 0.5,
          "matrix": [
            1,
            5
          ]
        },
        {
          "x": 7.25,
          "y": 4.25,
          "w": 0.5,
          "h": 0.5,
          "matrix": [
            0,
            11
          ]
        },
        {
          "x": 7.75,
          "y": 3.75,
          "w": 0.5,
          "h": 0.5,
          "matrix": [
            0,
            5
          ]
        },
        {
          "x": 9.25,
          "y": 4.25,
          "w": 0.5,
          "h": 0.5,
          "matrix": [
            2,
            11
          ]
        },
        {
          "x": 8.75,
          "y": 3.75,
          "w": 0.5,
          "h": 0.5,
          "matrix": [
            1,
            11
          ]
        },
        {
          "x": 9.25,
          "y": 3.75,
          "w": 0.5,
          "h": 0.5,
          "matrix": [
            3,
            11
          ]
        },
        {
          "x": 9.75,
          "y": 3.75,
          "w": 0.5,
          "h": 0.5,
          "matrix": [
            4,
            11
          ]
        },
        {
          "x": 9.25,
          "y": 3.25,
          "w": 0.5,
          "h": 0.5,
          "matrix": [
            3,
            5
          ]
        },
        {
          "x": 3.35,
          "y": 3,
          "matrix": [
            6,
            0
          ]
        },
        {
          "x": 12.6,
          "y": 3,
          "matrix": [
            6,
            6
          ]
        }
      ]
    }
  }
}